my_package_mprox/__init__.py
my_package_mprox-0.1.2.dist-info/WHEEL
my_package_mprox-0.1.2.dist-info/METADATA
my_package_mprox-0.1.2.dist-info/RECORD
