Metadata-Version: 2.1
Name: my-package-mprox
Version: 0.1.2
Summary: 
Author: MProx
Author-email: fake@nomail.com
Requires-Python: >=3.9,<4.0
Classifier: Programming Language :: Python :: 3
Classifier: Programming Language :: Python :: 3.9
Classifier: Programming Language :: Python :: 3.10
Classifier: Programming Language :: Python :: 3.11
Provides-Extra: boto3
Requires-Dist: boto3 (==1.24.89); extra == "boto3"
Requires-Dist: requests (>=2.28.1,<3.0.0)
